{
  "global": {
    "base": {
      "white": {
        "value": "#ffffff",
        "type": "color"
      },
      "black": {
        "value": "#000000",
        "type": "color"
      }
    },
    "opacity": {
      "white": {
        "12": {
          "value": "#ffffff1f",
          "type": "color"
        },
        "24": {
          "value": "#ffffff3d",
          "type": "color"
        },
        "48": {
          "value": "#ffffff7a",
          "type": "color"
        },
        "56": {
          "value": "#ffffff8f",
          "type": "color"
        },
        "76": {
          "value": "#ffffffc2",
          "type": "color"
        },
        "84": {
          "value": "#ffffffd6",
          "type": "color"
        }
      },
      "black": {
        "4": {
          "value": "#0000000a",
          "type": "color"
        },
        "8": {
          "value": "#00000014",
          "type": "color"
        },
        "16": {
          "value": "#00000029",
          "type": "color"
        },
        "56": {
          "value": "#0000008f",
          "type": "color"
        },
        "76": {
          "value": "#000000c2",
          "type": "color"
        },
        "84": {
          "value": "#000000d6",
          "type": "color"
        }
      }
    },
    "gray": {
      "100": {
        "value": "#f8f9fb",
        "type": "color"
      },
      "200": {
        "value": "#e8ebf2",
        "type": "color"
      },
      "300": {
        "value": "#98a1b3",
        "type": "color"
      },
      "400": {
        "value": "#363f50",
        "type": "color"
      },
      "500": {
        "value": "#101623",
        "type": "color"
      }
    },
    "blue": {
      "100": {
        "value": "#eff4ff",
        "type": "color"
      },
      "200": {
        "value": "#b2ccff",
        "type": "color"
      },
      "300": {
        "value": "#6699ff",
        "type": "color"
      },
      "400": {
        "value": "#0f51d7",
        "type": "color"
      },
      "500": {
        "value": "#082868",
        "type": "color"
      }
    },
    "red": {
      "100": {
        "value": "#fef3f2",
        "type": "color"
      },
      "200": {
        "value": "#fed1ca",
        "type": "color"
      },
      "300": {
        "value": "#fa6852",
        "type": "color"
      },
      "400": {
        "value": "#c8341e",
        "type": "color"
      },
      "500": {
        "value": "#470a00",
        "type": "color"
      }
    },
    "Shadow": {
      "Tiny": {
        "value": {
          "color": "#0000001a",
          "type": "dropShadow",
          "x": 0,
          "y": 2,
          "blur": 8,
          "spread": 0
        },
        "type": "boxShadow"
      },
      "Small": {
        "value": {
          "color": "#0000001f",
          "type": "dropShadow",
          "x": 0,
          "y": 8,
          "blur": 20,
          "spread": 0
        },
        "type": "boxShadow"
      },
      "Medium": {
        "value": {
          "color": "#0000001f",
          "type": "dropShadow",
          "x": 0,
          "y": 16,
          "blur": 40,
          "spread": 0
        },
        "type": "boxShadow"
      },
      "Large": {
        "value": {
          "color": "#0000001f",
          "type": "dropShadow",
          "x": 0,
          "y": 32,
          "blur": 80,
          "spread": 0
        },
        "type": "boxShadow"
      }
    },
    "fontFamilies": {
      "inter": {
        "value": "Inter",
        "type": "fontFamilies"
      }
    },
    "lineHeights": {
      "0": {
        "value": "130%",
        "type": "lineHeights"
      },
      "1": {
        "value": "120%",
        "type": "lineHeights"
      },
      "2": {
        "value": "110%",
        "type": "lineHeights"
      },
      "3": {
        "value": "100%",
        "type": "lineHeights"
      },
      "4": {
        "value": "150%",
        "type": "lineHeights"
      },
      "5": {
        "value": "175%",
        "type": "lineHeights"
      },
      "6": {
        "value": "125%",
        "type": "lineHeights"
      },
      "7": {
        "value": "140%",
        "type": "lineHeights"
      }
    },
    "fontWeights": {
      "inter-0": {
        "value": "Semi Bold",
        "type": "fontWeights"
      },
      "inter-1": {
        "value": "Medium",
        "type": "fontWeights"
      },
      "inter-2": {
        "value": "Regular",
        "type": "fontWeights"
      },
      "roboto-mono-3": {
        "value": "Regular",
        "type": "fontWeights"
      }
    },
    "fontSize": {
      "0": {
        "value": "14",
        "type": "fontSizes"
      },
      "1": {
        "value": "16",
        "type": "fontSizes"
      },
      "2": {
        "value": "18",
        "type": "fontSizes"
      },
      "3": {
        "value": "20",
        "type": "fontSizes"
      },
      "4": {
        "value": "24",
        "type": "fontSizes"
      },
      "5": {
        "value": "28",
        "type": "fontSizes"
      },
      "6": {
        "value": "32",
        "type": "fontSizes"
      },
      "7": {
        "value": "36",
        "type": "fontSizes"
      },
      "8": {
        "value": "38",
        "type": "fontSizes"
      },
      "9": {
        "value": "48",
        "type": "fontSizes"
      },
      "10": {
        "value": "56",
        "type": "fontSizes"
      },
      "11": {
        "value": "64",
        "type": "fontSizes"
      },
      "12": {
        "value": "72",
        "type": "fontSizes"
      },
      "13": {
        "value": "80",
        "type": "fontSizes"
      },
      "14": {
        "value": "100",
        "type": "fontSizes"
      },
      "15": {
        "value": "104",
        "type": "fontSizes"
      }
    },
    "letterSpacing": {
      "0": {
        "value": "0%",
        "type": "letterSpacing"
      },
      "1": {
        "value": "-2%",
        "type": "letterSpacing"
      },
      "2": {
        "value": "1%",
        "type": "letterSpacing"
      },
      "3": {
        "value": "0",
        "type": "letterSpacing"
      },
      "4": {
        "value": "-3",
        "type": "letterSpacing"
      }
    },
    "paragraphSpacing": {
      "0": {
        "value": "0",
        "type": "paragraphSpacing"
      },
      "1": {
        "value": "7",
        "type": "paragraphSpacing"
      },
      "2": {
        "value": "8",
        "type": "paragraphSpacing"
      },
      "3": {
        "value": "9",
        "type": "paragraphSpacing"
      },
      "4": {
        "value": "10",
        "type": "paragraphSpacing"
      },
      "5": {
        "value": "12",
        "type": "paragraphSpacing"
      },
      "6": {
        "value": "18",
        "type": "paragraphSpacing"
      },
      "7": {
        "value": "24",
        "type": "paragraphSpacing"
      }
    },
    "Typescale": {
      "Display": {
        "Display 1": {
          "value": {
            "fontFamily": "{fontFamilies.inter}",
            "fontWeight": "{fontWeights.inter-0}",
            "lineHeight": "{lineHeights.0}",
            "fontSize": "{fontSize.15}",
            "letterSpacing": "{letterSpacing.0}",
            "paragraphSpacing": "{paragraphSpacing.0}",
            "textCase": "{textCase.none}",
            "textDecoration": "{textDecoration.none}"
          },
          "type": "typography"
        },
        "Display 2": {
          "value": {
            "fontFamily": "{fontFamilies.inter}",
            "fontWeight": "{fontWeights.inter-0}",
            "lineHeight": "{lineHeights.1}",
            "fontSize": "{fontSize.13}",
            "letterSpacing": "{letterSpacing.0}",
            "paragraphSpacing": "{paragraphSpacing.0}",
            "textCase": "{textCase.none}",
            "textDecoration": "{textDecoration.none}"
          },
          "type": "typography"
        }
      },
      "Heading": {
        "Heading 1": {
          "value": {
            "fontFamily": "{fontFamilies.inter}",
            "fontWeight": "{fontWeights.inter-0}",
            "lineHeight": "{lineHeights.2}",
            "fontSize": "{fontSize.11}",
            "letterSpacing": "{letterSpacing.0}",
            "paragraphSpacing": "{paragraphSpacing.0}",
            "textCase": "{textCase.none}",
            "textDecoration": "{textDecoration.none}"
          },
          "type": "typography"
        },
        "Heading 2": {
          "value": {
            "fontFamily": "{fontFamilies.inter}",
            "fontWeight": "{fontWeights.inter-0}",
            "lineHeight": "{lineHeights.0}",
            "fontSize": "{fontSize.10}",
            "letterSpacing": "{letterSpacing.0}",
            "paragraphSpacing": "{paragraphSpacing.0}",
            "textCase": "{textCase.none}",
            "textDecoration": "{textDecoration.none}"
          },
          "type": "typography"
        },
        "Heading 3": {
          "value": {
            "fontFamily": "{fontFamilies.inter}",
            "fontWeight": "{fontWeights.inter-0}",
            "lineHeight": "{lineHeights.0}",
            "fontSize": "{fontSize.8}",
            "letterSpacing": "{letterSpacing.0}",
            "paragraphSpacing": "{paragraphSpacing.0}",
            "textCase": "{textCase.none}",
            "textDecoration": "{textDecoration.none}"
          },
          "type": "typography"
        },
        "Heading 4": {
          "value": {
            "fontFamily": "{fontFamilies.inter}",
            "fontWeight": "{fontWeights.inter-0}",
            "lineHeight": "{lineHeights.0}",
            "fontSize": "{fontSize.6}",
            "letterSpacing": "{letterSpacing.0}",
            "paragraphSpacing": "{paragraphSpacing.7}",
            "textCase": "{textCase.none}",
            "textDecoration": "{textDecoration.none}"
          },
          "type": "typography"
        },
        "Heading 5": {
          "value": {
            "fontFamily": "{fontFamilies.inter}",
            "fontWeight": "{fontWeights.inter-0}",
            "lineHeight": "{lineHeights.0}",
            "fontSize": "{fontSize.5}",
            "letterSpacing": "{letterSpacing.0}",
            "paragraphSpacing": "{paragraphSpacing.6}",
            "textCase": "{textCase.none}",
            "textDecoration": "{textDecoration.none}"
          },
          "type": "typography"
        },
        "Heading 6": {
          "value": {
            "fontFamily": "{fontFamilies.inter}",
            "fontWeight": "{fontWeights.inter-0}",
            "lineHeight": "{lineHeights.0}",
            "fontSize": "{fontSize.4}",
            "letterSpacing": "{letterSpacing.0}",
            "paragraphSpacing": "{paragraphSpacing.5}",
            "textCase": "{textCase.none}",
            "textDecoration": "{textDecoration.none}"
          },
          "type": "typography"
        }
      },
      "Label": {
        "Label 24": {
          "value": {
            "fontFamily": "{fontFamilies.inter}",
            "fontWeight": "{fontWeights.inter-0}",
            "lineHeight": "{lineHeights.3}",
            "fontSize": "{fontSize.4}",
            "letterSpacing": "{letterSpacing.1}",
            "paragraphSpacing": "{paragraphSpacing.5}",
            "textCase": "{textCase.none}",
            "textDecoration": "{textDecoration.none}"
          },
          "type": "typography"
        },
        "Label 20": {
          "value": {
            "fontFamily": "{fontFamilies.inter}",
            "fontWeight": "{fontWeights.inter-1}",
            "lineHeight": "{lineHeights.3}",
            "fontSize": "{fontSize.3}",
            "letterSpacing": "{letterSpacing.0}",
            "paragraphSpacing": "{paragraphSpacing.4}",
            "textCase": "{textCase.none}",
            "textDecoration": "{textDecoration.none}"
          },
          "type": "typography"
        },
        "Label 18": {
          "value": {
            "fontFamily": "{fontFamilies.inter}",
            "fontWeight": "{fontWeights.inter-1}",
            "lineHeight": "{lineHeights.3}",
            "fontSize": "{fontSize.2}",
            "letterSpacing": "{letterSpacing.0}",
            "paragraphSpacing": "{paragraphSpacing.3}",
            "textCase": "{textCase.none}",
            "textDecoration": "{textDecoration.none}"
          },
          "type": "typography"
        },
        "Label 16": {
          "value": {
            "fontFamily": "{fontFamilies.inter}",
            "fontWeight": "{fontWeights.inter-1}",
            "lineHeight": "{lineHeights.3}",
            "fontSize": "{fontSize.1}",
            "letterSpacing": "{letterSpacing.0}",
            "paragraphSpacing": "{paragraphSpacing.2}",
            "textCase": "{textCase.none}",
            "textDecoration": "{textDecoration.none}"
          },
          "type": "typography"
        },
        "Label 14": {
          "value": {
            "fontFamily": "{fontFamilies.inter}",
            "fontWeight": "{fontWeights.inter-1}",
            "lineHeight": "{lineHeights.3}",
            "fontSize": "{fontSize.0}",
            "letterSpacing": "{letterSpacing.0}",
            "paragraphSpacing": "{paragraphSpacing.2}",
            "textCase": "{textCase.none}",
            "textDecoration": "{textDecoration.none}"
          },
          "type": "typography"
        }
      },
      "Paragraph": {
        "Paragraph 24": {
          "value": {
            "fontFamily": "{fontFamilies.inter}",
            "fontWeight": "{fontWeights.inter-2}",
            "lineHeight": "{lineHeights.4}",
            "fontSize": "{fontSize.4}",
            "letterSpacing": "{letterSpacing.0}",
            "paragraphSpacing": "{paragraphSpacing.5}",
            "textCase": "{textCase.none}",
            "textDecoration": "{textDecoration.none}"
          },
          "type": "typography"
        },
        "Paragraph 20": {
          "value": {
            "fontFamily": "{fontFamilies.inter}",
            "fontWeight": "{fontWeights.inter-2}",
            "lineHeight": "{lineHeights.4}",
            "fontSize": "{fontSize.3}",
            "letterSpacing": "{letterSpacing.0}",
            "paragraphSpacing": "{paragraphSpacing.4}",
            "textCase": "{textCase.none}",
            "textDecoration": "{textDecoration.none}"
          },
          "type": "typography"
        },
        "Paragraph 18": {
          "value": {
            "fontFamily": "{fontFamilies.inter}",
            "fontWeight": "{fontWeights.inter-2}",
            "lineHeight": "{lineHeights.4}",
            "fontSize": "{fontSize.2}",
            "letterSpacing": "{letterSpacing.0}",
            "paragraphSpacing": "{paragraphSpacing.3}",
            "textCase": "{textCase.none}",
            "textDecoration": "{textDecoration.none}"
          },
          "type": "typography"
        },
        "Paragraph 16": {
          "value": {
            "fontFamily": "{fontFamilies.inter}",
            "fontWeight": "{fontWeights.inter-2}",
            "lineHeight": "{lineHeights.0}",
            "fontSize": "{fontSize.1}",
            "letterSpacing": "{letterSpacing.2}",
            "paragraphSpacing": "{paragraphSpacing.2}",
            "textCase": "{textCase.none}",
            "textDecoration": "{textDecoration.none}"
          },
          "type": "typography"
        },
        "Caption 14˙": {
          "value": {
            "fontFamily": "{fontFamilies.inter}",
            "fontWeight": "{fontWeights.inter-2}",
            "lineHeight": "{lineHeights.0}",
            "fontSize": "{fontSize.0}",
            "letterSpacing": "{letterSpacing.3}",
            "paragraphSpacing": "{paragraphSpacing.1}",
            "textCase": "{textCase.none}",
            "textDecoration": "{textDecoration.none}"
          },
          "type": "typography"
        },
        "Link 24": {
          "value": {
            "fontFamily": "{fontFamilies.inter}",
            "fontWeight": "{fontWeights.inter-2}",
            "lineHeight": "{lineHeights.5}",
            "fontSize": "{fontSize.4}",
            "letterSpacing": "{letterSpacing.0}",
            "paragraphSpacing": "{paragraphSpacing.5}",
            "textCase": "{textCase.none}",
            "textDecoration": "{textDecoration.underline}"
          },
          "type": "typography"
        },
        "Link 20": {
          "value": {
            "fontFamily": "{fontFamilies.inter}",
            "fontWeight": "{fontWeights.inter-2}",
            "lineHeight": "{lineHeights.5}",
            "fontSize": "{fontSize.3}",
            "letterSpacing": "{letterSpacing.0}",
            "paragraphSpacing": "{paragraphSpacing.4}",
            "textCase": "{textCase.none}",
            "textDecoration": "{textDecoration.underline}"
          },
          "type": "typography"
        },
        "Link 18": {
          "value": {
            "fontFamily": "{fontFamilies.inter}",
            "fontWeight": "{fontWeights.inter-2}",
            "lineHeight": "{lineHeights.5}",
            "fontSize": "{fontSize.2}",
            "letterSpacing": "{letterSpacing.0}",
            "paragraphSpacing": "{paragraphSpacing.3}",
            "textCase": "{textCase.none}",
            "textDecoration": "{textDecoration.underline}"
          },
          "type": "typography"
        },
        "Link 16": {
          "value": {
            "fontFamily": "{fontFamilies.inter}",
            "fontWeight": "{fontWeights.inter-2}",
            "lineHeight": "{lineHeights.5}",
            "fontSize": "{fontSize.1}",
            "letterSpacing": "{letterSpacing.2}",
            "paragraphSpacing": "{paragraphSpacing.0}",
            "textCase": "{textCase.none}",
            "textDecoration": "{textDecoration.underline}"
          },
          "type": "typography"
        },
        "Link Caption 14": {
          "value": {
            "fontFamily": "{fontFamilies.inter}",
            "fontWeight": "{fontWeights.inter-2}",
            "lineHeight": "{lineHeights.6}",
            "fontSize": "{fontSize.0}",
            "letterSpacing": "{letterSpacing.1}",
            "paragraphSpacing": "{paragraphSpacing.1}",
            "textCase": "{textCase.none}",
            "textDecoration": "{textDecoration.underline}"
          },
          "type": "typography"
        }
      }
    },
    "Rich Text": {
      "H1": {
        "value": {
          "fontFamily": "{fontFamilies.inter}",
          "fontWeight": "{fontWeights.inter-0}",
          "lineHeight": "{lineHeights.2}",
          "fontSize": "{fontSize.14}",
          "letterSpacing": "{letterSpacing.0}",
          "paragraphSpacing": "{paragraphSpacing.0}",
          "textCase": "{textCase.none}",
          "textDecoration": "{textDecoration.none}"
        },
        "type": "typography"
      },
      "H2": {
        "value": {
          "fontFamily": "{fontFamilies.inter}",
          "fontWeight": "{fontWeights.inter-0}",
          "lineHeight": "{lineHeights.2}",
          "fontSize": "{fontSize.12}",
          "letterSpacing": "{letterSpacing.0}",
          "paragraphSpacing": "{paragraphSpacing.0}",
          "textCase": "{textCase.none}",
          "textDecoration": "{textDecoration.none}"
        },
        "type": "typography"
      },
      "H3": {
        "value": {
          "fontFamily": "{fontFamilies.inter}",
          "fontWeight": "{fontWeights.inter-0}",
          "lineHeight": "{lineHeights.2}",
          "fontSize": "{fontSize.11}",
          "letterSpacing": "{letterSpacing.0}",
          "paragraphSpacing": "{paragraphSpacing.0}",
          "textCase": "{textCase.none}",
          "textDecoration": "{textDecoration.none}"
        },
        "type": "typography"
      },
      "H4": {
        "value": {
          "fontFamily": "{fontFamilies.inter}",
          "fontWeight": "{fontWeights.inter-0}",
          "lineHeight": "{lineHeights.7}",
          "fontSize": "{fontSize.9}",
          "letterSpacing": "{letterSpacing.0}",
          "paragraphSpacing": "{paragraphSpacing.0}",
          "textCase": "{textCase.none}",
          "textDecoration": "{textDecoration.none}"
        },
        "type": "typography"
      },
      "H5": {
        "value": {
          "fontFamily": "{fontFamilies.inter}",
          "fontWeight": "{fontWeights.inter-0}",
          "lineHeight": "{lineHeights.7}",
          "fontSize": "{fontSize.7}",
          "letterSpacing": "{letterSpacing.0}",
          "paragraphSpacing": "{paragraphSpacing.0}",
          "textCase": "{textCase.none}",
          "textDecoration": "{textDecoration.none}"
        },
        "type": "typography"
      },
      "H6": {
        "value": {
          "fontFamily": "{fontFamilies.inter}",
          "fontWeight": "{fontWeights.inter-0}",
          "lineHeight": "{lineHeights.7}",
          "fontSize": "{fontSize.4}",
          "letterSpacing": "{letterSpacing.0}",
          "paragraphSpacing": "{paragraphSpacing.0}",
          "textCase": "{textCase.none}",
          "textDecoration": "{textDecoration.none}"
        },
        "type": "typography"
      },
      "Blockquote": {
        "value": {
          "fontFamily": "{fontFamilies.inter}",
          "fontWeight": "{fontWeights.inter-2}",
          "lineHeight": "{lineHeights.5}",
          "fontSize": "{fontSize.4}",
          "letterSpacing": "{letterSpacing.0}",
          "paragraphSpacing": "{paragraphSpacing.5}",
          "textCase": "{textCase.none}",
          "textDecoration": "{textDecoration.none}"
        },
        "type": "typography"
      },
      "Image Caption": {
        "value": {
          "fontFamily": "{fontFamilies.inter}",
          "fontWeight": "{fontWeights.inter-2}",
          "lineHeight": "{lineHeights.6}",
          "fontSize": "{fontSize.0}",
          "letterSpacing": "{letterSpacing.0}",
          "paragraphSpacing": "{paragraphSpacing.1}",
          "textCase": "{textCase.none}",
          "textDecoration": "{textDecoration.none}"
        },
        "type": "typography"
      },
      "List": {
        "value": {
          "fontFamily": "{fontFamilies.inter}",
          "fontWeight": "{fontWeights.inter-2}",
          "lineHeight": "{lineHeights.5}",
          "fontSize": "{fontSize.2}",
          "letterSpacing": "{letterSpacing.0}",
          "paragraphSpacing": "{paragraphSpacing.3}",
          "textCase": "{textCase.none}",
          "textDecoration": "{textDecoration.none}"
        },
        "type": "typography"
      },
      "Paragraph": {
        "value": {
          "fontFamily": "{fontFamilies.inter}",
          "fontWeight": "{fontWeights.inter-2}",
          "lineHeight": "{lineHeights.5}",
          "fontSize": "{fontSize.2}",
          "letterSpacing": "{letterSpacing.0}",
          "paragraphSpacing": "{paragraphSpacing.3}",
          "textCase": "{textCase.none}",
          "textDecoration": "{textDecoration.none}"
        },
        "type": "typography"
      }
    },
    "Label": {
      "Pricing": {
        "value": {
          "fontFamily": "{fontFamilies.inter}",
          "fontWeight": "{fontWeights.inter-0}",
          "lineHeight": "{lineHeights.0}",
          "fontSize": "{fontSize.8}",
          "letterSpacing": "{letterSpacing.4}",
          "paragraphSpacing": "{paragraphSpacing.0}",
          "textCase": "{textCase.none}",
          "textDecoration": "{textDecoration.none}"
        },
        "type": "typography"
      }
    },
    "textCase": {
      "none": {
        "value": "none",
        "type": "textCase"
      }
    },
    "textDecoration": {
      "none": {
        "value": "none",
        "type": "textDecoration"
      },
      "underline": {
        "value": "underline",
        "type": "textDecoration"
      }
    },
    "purple": {
      "100": {
        "value": "#f7f5ff",
        "type": "color"
      },
      "200": {
        "value": "#e0d7fe",
        "type": "color"
      },
      "300": {
        "value": "#ae97f6",
        "type": "color"
      },
      "400": {
        "value": "#5633c8",
        "type": "color"
      },
      "500": {
        "value": "#270986",
        "type": "color"
      }
    }
  },
  "default": {
    "Foreground": {
      "Primary": {
        "value": "{opacity.black.84}",
        "type": "color"
      },
      "Secondary": {
        "value": "{opacity.black.76}",
        "type": "color"
      },
      "Tertiary": {
        "value": "{opacity.black.56}",
        "type": "color"
      },
      "Inverse Primary": {
        "value": "{base.white}",
        "type": "color"
      },
      "Inverse Secondary": {
        "value": "{opacity.white.76}",
        "type": "color"
      },
      "Inverse Tertiary": {
        "value": "{opacity.white.56}",
        "type": "color"
      },
      "Interactive": {
        "value": "{blue.400}",
        "type": "color"
      },
      "Interactive Hover": {
        "value": "{blue.500}",
        "type": "color"
      },
      "Disabled": {
        "value": "{gray.300}",
        "type": "color"
      }
    },
    "Background": {
      "Primary": {
        "value": "{base.white}",
        "type": "color"
      },
      "Secondary": {
        "value": "{blue.100}",
        "type": "color"
      },
      "Interactive": {
        "value": "{blue.400}",
        "type": "color"
      },
      "Interactive Hover": {
        "value": "{blue.500}",
        "type": "color"
      },
      "Interactive Secondary": {
        "value": "{blue.100}",
        "type": "color"
      },
      "Interactive Secondary Hover": {
        "value": "{blue.200}",
        "type": "color"
      },
      "Interactive Tertiary Hover": {
        "value": "{blue.100}",
        "type": "color"
      },
      "System Negative": {
        "value": "{red.200}",
        "type": "color"
      },
      "Accents": {
        "Brand Blue": {
          "value": "{blue.400}",
          "type": "color"
        },
        "Brand Dark Blue": {
          "value": "{blue.500}",
          "type": "color"
        }
      }
    },
    "Borders": {
      "Default": {
        "value": "{opacity.black.16}",
        "type": "color"
      },
      "Hover": {
        "value": "{opacity.black.56}",
        "type": "color"
      },
      "Selected": {
        "value": "{opacity.black.84}",
        "type": "color"
      },
      "Focus": {
        "value": "{blue.400}",
        "type": "color"
      }
    }
  },
  "purple": {
    "Foreground": {
      "Primary": {
        "value": "{opacity.black.84}",
        "type": "color"
      },
      "Secondary": {
        "value": "{opacity.black.76}",
        "type": "color"
      },
      "Tertiary": {
        "value": "{opacity.black.56}",
        "type": "color"
      },
      "Inverse Primary": {
        "value": "{base.white}",
        "type": "color"
      },
      "Inverse Secondary": {
        "value": "{opacity.white.76}",
        "type": "color"
      },
      "Inverse Tertiary": {
        "value": "{opacity.white.56}",
        "type": "color"
      },
      "Interactive": {
        "value": "{purple.400}",
        "type": "color"
      },
      "Interactive Hover": {
        "value": "{purple.500}",
        "type": "color"
      },
      "Disabled": {
        "value": "{gray.300}",
        "type": "color"
      }
    },
    "Background": {
      "Primary": {
        "value": "{base.white}",
        "type": "color"
      },
      "Secondary": {
        "value": "{purple.100}",
        "type": "color"
      },
      "Interactive": {
        "value": "{purple.400}",
        "type": "color"
      },
      "Interactive Hover": {
        "value": "{purple.500}",
        "type": "color"
      },
      "Interactive Secondary": {
        "value": "{purple.100}",
        "type": "color"
      },
      "Interactive Secondary Hover": {
        "value": "{purple.200}",
        "type": "color"
      },
      "Interactive Tertiary Hover": {
        "value": "{purple.100}",
        "type": "color"
      },
      "System Negative": {
        "value": "{red.200}",
        "type": "color"
      },
      "Accents": {
        "Brand Blue": {
          "value": "{purple.400}",
          "type": "color"
        },
        "Brand Dark Blue": {
          "value": "{purple.500}",
          "type": "color"
        }
      }
    },
    "Borders": {
      "Default": {
        "value": "{opacity.black.16}",
        "type": "color"
      },
      "Hover": {
        "value": "{opacity.black.56}",
        "type": "color"
      },
      "Selected": {
        "value": "{opacity.black.84}",
        "type": "color"
      },
      "Focus": {
        "value": "{purple.400}",
        "type": "color"
      }
    }
  },
  "$themes": [],
  "$metadata": {
    "tokenSetOrder": [
      "global",
      "default",
      "purple"
    ]
  }
}